wifi_password_viewer/__init__.py
wifi_password_viewer/core.py
wifi_password_viewer-1.0.1.dist-info/METADATA
wifi_password_viewer-1.0.1.dist-info/WHEEL
wifi_password_viewer-1.0.1.dist-info/RECORD
